odoo/addons/hr_employee_age/README.rst
odoo/addons/hr_employee_age/__init__.py
odoo/addons/hr_employee_age/__manifest__.py
odoo/addons/hr_employee_age/i18n/ar.po
odoo/addons/hr_employee_age/i18n/cs_CZ.po
odoo/addons/hr_employee_age/i18n/de.po
odoo/addons/hr_employee_age/i18n/es.po
odoo/addons/hr_employee_age/i18n/fi.po
odoo/addons/hr_employee_age/i18n/fr.po
odoo/addons/hr_employee_age/i18n/hr.po
odoo/addons/hr_employee_age/i18n/hr_HR.po
odoo/addons/hr_employee_age/i18n/hr_employee_age.pot
odoo/addons/hr_employee_age/i18n/it.po
odoo/addons/hr_employee_age/i18n/lt.po
odoo/addons/hr_employee_age/i18n/nl_NL.po
odoo/addons/hr_employee_age/i18n/pt_BR.po
odoo/addons/hr_employee_age/i18n/ro.po
odoo/addons/hr_employee_age/i18n/sl.po
odoo/addons/hr_employee_age/models/__init__.py
odoo/addons/hr_employee_age/models/hr_employee.py
odoo/addons/hr_employee_age/readme/CONTRIBUTORS.md
odoo/addons/hr_employee_age/readme/DESCRIPTION.md
odoo/addons/hr_employee_age/readme/USAGE.md
odoo/addons/hr_employee_age/static/description/icon.png
odoo/addons/hr_employee_age/static/description/index.html
odoo/addons/hr_employee_age/tests/__init__.py
odoo/addons/hr_employee_age/tests/test_hr_employee.py
odoo/addons/hr_employee_age/views/hr_employee.xml
odoo_addon_hr_employee_age-18.0.1.0.0.2.dist-info/METADATA
odoo_addon_hr_employee_age-18.0.1.0.0.2.dist-info/WHEEL
odoo_addon_hr_employee_age-18.0.1.0.0.2.dist-info/top_level.txt
odoo_addon_hr_employee_age-18.0.1.0.0.2.dist-info/RECORD
